{
  "@context": "http://iiif.io/api/presentation/2/context.json",
  "@id": "https://nakala.fr/iiif/10.34847/nkl.ebe8f651/manifest",
  "@type": "sc:Manifest",
  "label": "SPA_2488",
  "attribution": "Nicolas Moron / NAKALA",
  "license": "http://creativecommons.org/licenses/by-nc/4.0/",
  "logo": "https://nakala.fr/logo/",
  "metadata": [
    {
      "label": "Id",
      "value": "SPA_2488"
    },
    {
      "label": "Title",
      "value": "SPA_2488 Letter from Ernest Alexandrovich Oeberg to Sergey Sergeevich Prokofiev"
    },
    {
      "label": "Creator",
      "value": "Ernest Alexandrovich Oeberg"
    },
    {
      "label": "Date Issued",
      "value": "1924-01-09"
    },
    {
      "label": "Type",
      "value": "manuscript"
    }
  ],
  "sequences": [
    {
      "@id": "https://nakala.fr/iiif/10.34847/nkl.ebe8f651/sequence/normal",
      "@type": "sc:Sequence",
      "label": "SPA_2488",
      "viewingHint": "paged",
      "startCanvas": "https://nakala.fr/iiif/10.34847/nkl.ebe8f651/canvas/page1",
      "canvases": [
        {
          "@id": "https://nakala.fr/iiif/10.34847/nkl.ebe8f651/canvas/page1",
          "@type": "sc:Canvas",
          "label": "Page 1",
          "height": 6870,
          "width": 5405,
          "thumbnail": {
            "@id": "https://api.nakala.fr/iiif/10.34847/nkl.ebe8f651/9381d78fd82a04081efad7496b1a88c53f70f1a1/full/,150/0/default.jpg",
            "@type": "dctypes:Image"
          },
          "images": [
            {
              "@id": "https://nakala.fr/iiif/10.34847/nkl.ebe8f651/annotation/page1",
              "@type": "oa:Annotation",
              "motivation": "sc:painting",
              "on": "https://nakala.fr/iiif/10.34847/nkl.ebe8f651/canvas/page1",
              "resource": {
                "@id": "https://api.nakala.fr/iiif/10.34847/nkl.ebe8f651/9381d78fd82a04081efad7496b1a88c53f70f1a1/full/full/0/default.jpg",
                "@type": "dctypes:Image",
                "format": "image/jpeg",
                "height": 6870,
                "width": 5405,
                "service": {
                  "@context": "http://iiif.io/api/image/2/context.json",
                  "@id": "https://api.nakala.fr/iiif/10.34847/nkl.ebe8f651/9381d78fd82a04081efad7496b1a88c53f70f1a1",
                  "profile": "http://iiif.io/api/image/2/level2.json"
                }
              }
            }
          ]
        }
      ]
    }
  ]
}